MANIFEST.in
README.md
setup.cfg
setup.py
versioneer.py
deepmachine/__init__.py
deepmachine/_version.py
deepmachine/base.py
deepmachine/flags.py
deepmachine/io.py
deepmachine.egg-info/PKG-INFO
deepmachine.egg-info/SOURCES.txt
deepmachine.egg-info/dependency_links.txt
deepmachine.egg-info/requires.txt
deepmachine.egg-info/top_level.txt
deepmachine/callbacks/__init__.py
deepmachine/callbacks/base.py
deepmachine/contrib/__init__.py
deepmachine/contrib/training/3DMMCamera.py
deepmachine/contrib/training/CoMA.py
deepmachine/contrib/training/CycleGAN.py
deepmachine/contrib/training/DenseRegFace.py
deepmachine/contrib/training/DenseRegPose.py
deepmachine/contrib/training/FaceUVAutoEncoder.py
deepmachine/contrib/training/PRNet.py
deepmachine/contrib/training/Recognition.py
deepmachine/contrib/training/Recognition_estimator.py
deepmachine/contrib/training/StarGAN.py
deepmachine/contrib/training/UVMeshAE.py
deepmachine/contrib/training/__init__.py
deepmachine/contrib/training/estimator_3dmm.py
deepmachine/contrib/training/estimator_mesh_ae.py
deepmachine/contrib/training/estimator_mesh_ae_7k.py
deepmachine/contrib/training/estimator_mesh_ae_stress.py
deepmachine/contrib/training/keras_3DMM.py
deepmachine/data/__init__.py
deepmachine/data/builder/__init__.py
deepmachine/data/builder/base.py
deepmachine/data/builder/builder.py
deepmachine/data/builder/db_iterator.py
deepmachine/data/generator/__init__.py
deepmachine/data/generator/base.py
deepmachine/data/generator/preprocess.py
deepmachine/data/provider/__init__.py
deepmachine/data/provider/base.py
deepmachine/data/provider/features.py
deepmachine/data/provider/resolvers.py
deepmachine/engine/__init__.py
deepmachine/engine/training.py
deepmachine/layers/__init__.py
deepmachine/layers/base.py
deepmachine/layers/coord.py
deepmachine/layers/mesh.py
deepmachine/layers/mrcnn.py
deepmachine/layers/tfl.py
deepmachine/layers/mesh_renderer/__init__.py
deepmachine/layers/mesh_renderer/base.py
deepmachine/layers/mesh_renderer/demo.py
deepmachine/layers/mesh_renderer/mesh_renderer.py
deepmachine/layers/mesh_renderer/rasterize_triangles.py
deepmachine/losses/__init__.py
deepmachine/losses/base.py
