Metadata-Version: 1.0
Name: deepmachine
Version: 0.7.5
Summary: Deep Learning Framework
Home-page: https://github.com/yuxiang-zhou/deepmachine
Author: Yuxiang ZHOU
Author-email: mr.yuxiang.zhou@googlemail.com
License: UNKNOWN
Platform: UNKNOWN
